NetLink-0.1.dist-info/DESCRIPTION.rst
NetLink-0.1.dist-info/METADATA
NetLink-0.1.dist-info/RECORD
NetLink-0.1.dist-info/WHEEL
NetLink-0.1.dist-info/metadata.json
NetLink-0.1.dist-info/top_level.txt
netlink/__init__.py
netlink/low/ethtool.py
netlink/low/netif.py
netlink/low/netlink.py
netlink/low/netlinkattrib.py
netlink/struct/ethtool.py
netlink/struct/misc.py
netlink/struct/netif.py
netlink/struct/netlink.py
netlink/struct/routing.py
netlink/struct/socket.py
