Metadata-Version: 2.0
Name: NetLink
Version: 0.1
Summary: Pure-Python client for the Linux NetLink interface
Home-page: https://xmine128.tk/Software/Python/netlink/
Author: Alexander Schlarb
Author-email: alexander-devel@xmine128.tk
License: LGPL-3.0+
Platform: Linux
Classifier: Development Status :: 2 - Pre-Alpha
Classifier: Intended Audience :: Developers
Classifier: Intended Audience :: System Administrators
Classifier: License :: OSI Approved :: GNU Lesser General Public License v3 or later (LGPLv3+)
Classifier: Operating System :: POSIX :: Linux
Classifier: Programming Language :: Python :: 3 :: Only
Classifier: Programming Language :: Python :: 3.3
Classifier: Programming Language :: Python :: 3.4
Classifier: Programming Language :: Python :: 3.5
Classifier: Topic :: System :: Networking
Classifier: Topic :: System :: Networking :: Firewalls
Classifier: Topic :: System :: Operating System Kernels :: Linux
